vmwc/__init__.py
vmwc-1.0.6.dist-info/LICENSE.txt
vmwc-1.0.6.dist-info/METADATA
vmwc-1.0.6.dist-info/WHEEL
vmwc-1.0.6.dist-info/top_level.txt
vmwc-1.0.6.dist-info/RECORD
