Metadata-Version: 2.1
Name: vmwc
Version: 1.0.6
Summary: VMWare python client
Home-page: https://github.com/jossef/vmwc
Author: Jossef Harush
Author-email: jossef12@gmail.com
License: Apache v2
Keywords: vmwc vmware pyvmomi python client vix setuptools development
Platform: UNKNOWN
Classifier: Development Status :: 5 - Production/Stable
Classifier: Intended Audience :: Developers
Classifier: Topic :: Software Development :: Build Tools
Classifier: License :: OSI Approved :: Apache Software License
Classifier: Programming Language :: Python :: 2
Classifier: Programming Language :: Python :: 2.6
Classifier: Programming Language :: Python :: 2.7
Classifier: Programming Language :: Python :: 3
Classifier: Programming Language :: Python :: 3.3
Classifier: Programming Language :: Python :: 3.4
Classifier: Programming Language :: Python :: 3.5
License-File: LICENSE.txt
Requires-Dist: requests
Requires-Dist: pyvmomi (>=6.5)
Provides-Extra: dev
Requires-Dist: check-manifest ; extra == 'dev'
Provides-Extra: test
Requires-Dist: coverage ; extra == 'test'
